README.rst
setup.py
pyps4/__init__.py
pyps4/cli.py
pyps4/connection.py
pyps4/ddp.py
pyps4/errors.py
pyps4/ps4.py
pyps4/version.py
pyps4.egg-info/PKG-INFO
pyps4.egg-info/SOURCES.txt
pyps4.egg-info/dependency_links.txt
pyps4.egg-info/entry_points.txt
pyps4.egg-info/requires.txt
pyps4.egg-info/top_level.txt